testsavant/guard/__init__.py
testsavant/guard/_exceptions.py
testsavant/guard/guard.py
testsavant/guard/image_scanners/__init__.py
testsavant/guard/image_scanners/image_nsfw.py
testsavant/guard/image_scanners/text_redactor.py
testsavant/guard/input_scanners/__init__.py
testsavant/guard/input_scanners/anonymize.py
testsavant/guard/input_scanners/ban_code.py
testsavant/guard/input_scanners/ban_competitors.py
testsavant/guard/input_scanners/ban_substrings.py
testsavant/guard/input_scanners/ban_topics.py
testsavant/guard/input_scanners/base_scanner.py
testsavant/guard/input_scanners/code.py
testsavant/guard/input_scanners/gibberish.py
testsavant/guard/input_scanners/invisible_text.py
testsavant/guard/input_scanners/language.py
testsavant/guard/input_scanners/nsfw.py
testsavant/guard/input_scanners/prompt_injection.py
testsavant/guard/input_scanners/regex.py
testsavant/guard/input_scanners/secrets.py
testsavant/guard/input_scanners/sentiment.py
testsavant/guard/input_scanners/token_limit.py
testsavant/guard/input_scanners/toxicity.py
testsavant/guard/output_scanners/__init__.py
testsavant/guard/output_scanners/ban_code.py
testsavant/guard/output_scanners/ban_competitors.py
testsavant/guard/output_scanners/ban_substrings.py
testsavant/guard/output_scanners/ban_topics.py
testsavant/guard/output_scanners/bias.py
testsavant/guard/output_scanners/code.py
testsavant/guard/output_scanners/factual_consistency.py
testsavant/guard/output_scanners/gibberish.py
testsavant/guard/output_scanners/json.py
testsavant/guard/output_scanners/language.py
testsavant/guard/output_scanners/language_same.py
testsavant/guard/output_scanners/malicious_url.py
testsavant/guard/output_scanners/no_refusal.py
testsavant/guard/output_scanners/nsfw.py
testsavant/guard/output_scanners/prompt_injection.py
testsavant/guard/output_scanners/reading_time.py
testsavant/guard/output_scanners/regex.py
testsavant/guard/output_scanners/relevance.py
testsavant/guard/output_scanners/sensitive.py
testsavant_sdk-0.0.3.dist-info/licenses/LICENSE
testsavant_sdk-0.0.3.dist-info/METADATA
testsavant_sdk-0.0.3.dist-info/WHEEL
testsavant_sdk-0.0.3.dist-info/top_level.txt
testsavant_sdk-0.0.3.dist-info/RECORD
