Metadata-Version: 2.4
Name: testsavant-sdk
Version: 0.0.3
Summary: Test Savant SDK provides tools and utilities for interacting with the Test Savant platform, enabling seamless integration and development of AI applications.
Author-email: Test Savant SDK <support@testsavant.ai>
License-Expression: Apache-2.0
Project-URL: Homepage, https://github.com/TestSavantAI/ts-sdk
Project-URL: Issues, https://github.com/TestSavantAI/ts-sdk/issues
Classifier: Typing :: Typed
Classifier: Intended Audience :: Developers
Classifier: Programming Language :: Python :: 3.8
Classifier: Programming Language :: Python :: 3.9
Classifier: Programming Language :: Python :: 3.10
Classifier: Programming Language :: Python :: 3.11
Classifier: Programming Language :: Python :: 3.12
Classifier: Programming Language :: Python :: 3.13
Classifier: Operating System :: OS Independent
Classifier: Operating System :: POSIX
Classifier: Operating System :: MacOS
Classifier: Operating System :: POSIX :: Linux
Classifier: Operating System :: Microsoft :: Windows
Classifier: Topic :: Software Development :: Libraries :: Python Modules
Requires-Python: >=3.8
License-File: LICENSE
Requires-Dist: httpx==0.28.1
Requires-Dist: pydantic==2.11.5
Dynamic: license-file
